covet_rust-0.1.0b2.dist-info/METADATA
covet_rust-0.1.0b2.dist-info/WHEEL
covet_rust/__init__.py
covet_rust/_internal.abi3.so
covet_rust-0.1.0b2.dist-info/RECORD
