Metadata-Version: 2.4
Name: covet-rust
Version: 0.1.0b2
Classifier: Development Status :: 4 - Beta
Classifier: Intended Audience :: Developers
Classifier: License :: Other/Proprietary License
Classifier: Programming Language :: Python :: 3
Classifier: Programming Language :: Python :: 3.9
Classifier: Programming Language :: Python :: 3.10
Classifier: Programming Language :: Python :: 3.11
Classifier: Programming Language :: Python :: 3.12
Classifier: Programming Language :: Rust
Classifier: Topic :: Internet :: WWW/HTTP
Classifier: Topic :: Software Development :: Libraries :: Python Modules
Classifier: Topic :: Database
Classifier: Topic :: Security :: Cryptography
Classifier: Operating System :: OS Independent
Classifier: Framework :: AsyncIO
Requires-Dist: pytest>=7.0 ; extra == 'dev'
Requires-Dist: pytest-asyncio>=0.21 ; extra == 'dev'
Requires-Dist: pytest-benchmark>=4.0 ; extra == 'dev'
Requires-Dist: pytest-cov>=4.0 ; extra == 'dev'
Requires-Dist: black>=23.0 ; extra == 'dev'
Requires-Dist: mypy>=1.0 ; extra == 'dev'
Requires-Dist: ruff>=0.1 ; extra == 'dev'
Requires-Dist: ipython>=8.0 ; extra == 'dev'
Requires-Dist: asyncpg>=0.29 ; extra == 'postgres'
Requires-Dist: aiomysql>=0.2 ; extra == 'mysql'
Requires-Dist: uvloop>=0.19 ; extra == 'bench'
Requires-Dist: orjson>=3.9 ; extra == 'bench'
Requires-Dist: ujson>=5.9 ; extra == 'bench'
Requires-Dist: covet-rust[dev,postgres,mysql,bench] ; extra == 'all'
Provides-Extra: dev
Provides-Extra: postgres
Provides-Extra: mysql
Provides-Extra: bench
Provides-Extra: all
Summary: High-performance Rust extensions for CovetPy web framework with comprehensive FFI
Keywords: web,framework,async,performance,rust,ffi,database,orm,cryptography,json
Author: Vipin Kumar
License: Proprietary
Requires-Python: >=3.9
Project-URL: Author, https://github.com/vipin08
Project-URL: Documentation, https://github.com/vipin08/Covet-doc
